pybotx_smart_logger/__init__.py
pybotx_smart_logger/contextvars.py
pybotx_smart_logger/log_levels.py
pybotx_smart_logger/logger.py
pybotx_smart_logger/py.typed
pybotx_smart_logger/schemas.py
pybotx_smart_logger/wrapper.py
pybotx_smart_logger-0.11.1.dist-info/LICENSE
pybotx_smart_logger-0.11.1.dist-info/METADATA
pybotx_smart_logger-0.11.1.dist-info/WHEEL
pybotx_smart_logger-0.11.1.dist-info/RECORD
