Metadata-Version: 2.3
Name: pybotx-smart-logger
Version: 0.11.1
Summary: Shows logs when you need it
Author: Alexander Samoylenko
Author-email: alexandr.samojlenko@ccsteam.ru
Requires-Python: >=3.9,<3.14
Classifier: Programming Language :: Python :: 3
Classifier: Programming Language :: Python :: 3.9
Classifier: Programming Language :: Python :: 3.10
Classifier: Programming Language :: Python :: 3.11
Classifier: Programming Language :: Python :: 3.12
Classifier: Programming Language :: Python :: 3.13
Requires-Dist: loguru (>=0.6.0,<0.7.0)
